[
  {
    "exercise" : "Брусок массой 440 г имеет размеры 20см Х 5см Х 2см. Какова плотность бруска (в г/см^3)?",
    "right_answer" : "2,2"
  },
  {
    "exercise" : "Свинцовый брусок массой 1,5 кг имеет длину 10см, ширину 6см. Какова его толщина (в см)?",
    "right_answer" : "2,2"
  },
  {
    "exercise" : "Оловянный брусок размерами 2см Х 2см Х 2см имеет ту же массу, что брусок размерами 3см Х 3см Х 1см. Какова плотность вещества, из которого сделан второй брусок(в г/см^3)?",
    "right_answer" : "6,5"
  }
]
